cross_auth/__init__.py
cross_auth/_context.py
cross_auth/_issuer.py
cross_auth/_route.py
cross_auth/_storage.py
cross_auth/exceptions.py
cross_auth/py.typed
cross_auth/router.py
cross_auth/models/__init__.py
cross_auth/models/oauth_token_response.py
cross_auth/social_providers/__init__.py
cross_auth/social_providers/discord.py
cross_auth/social_providers/github.py
cross_auth/social_providers/oauth.py
cross_auth/utils/__init__.py
cross_auth/utils/_is_same_host.py
cross_auth/utils/_pkce.py
cross_auth/utils/_response.py
cross_auth/utils/_url.py
cross_auth-0.2.0.dist-info/METADATA
cross_auth-0.2.0.dist-info/WHEEL
cross_auth-0.2.0.dist-info/RECORD
