Metadata-Version: 2.4
Name: cross-auth
Version: 0.2.0
Summary: A modern Authentication Framework for Python
Author-email: Patrick Arminio <patrick.arminio@gmail.com>
Requires-Python: >=3.11
Requires-Dist: bcrypt<5.0.0,>=4.0.0
Requires-Dist: lia-web>=0.1.2
Requires-Dist: passlib[bcrypt]>=1.7.4
Requires-Dist: pydantic[email]>=2.11.3
